gemseo_scilab/__init__.py
gemseo_scilab/py_scilab.py
gemseo_scilab/scilab_discipline.py
gemseo_scilab-3.0.1.dist-info/licenses/LICENSE.txt
gemseo_scilab-3.0.1.dist-info/METADATA
gemseo_scilab-3.0.1.dist-info/WHEEL
gemseo_scilab-3.0.1.dist-info/entry_points.txt
gemseo_scilab-3.0.1.dist-info/top_level.txt
gemseo_scilab-3.0.1.dist-info/RECORD
