Metadata-Version: 2.4
Name: gemseo-scilab
Version: 3.0.1
Summary: GEMSEO plugin to create disciplines from scilab source code.
Author-email: François Gallard <contact@gemseo.org>
License-Expression: LGPL-3.0
Project-URL: Homepage, https://gemseo.org
Project-URL: Source, https://gitlab.com/gemseo/dev/gemseo-scilab
Project-URL: Issues, https://gitlab.com/gemseo/dev/gemseo-scilab/-/issues
Classifier: Intended Audience :: Science/Research
Classifier: Topic :: Scientific/Engineering
Classifier: Operating System :: POSIX :: Linux
Classifier: Operating System :: MacOS
Classifier: Operating System :: Microsoft :: Windows
Classifier: Programming Language :: Python :: 3 :: Only
Classifier: Programming Language :: Python :: 3.10
Classifier: Programming Language :: Python :: 3.11
Requires-Python: <3.12,>=3.9
License-File: LICENSE.txt
Requires-Dist: gemseo[all]<7,>=6.3
Requires-Dist: numpy<1.24
Requires-Dist: scilab2py==0.6.2
Dynamic: license-file
